password_generator/__init__.py
password_generator/__main__.py
password_generator/generate.py
password_generator_imbev-1.0.0.dist-info/entry_points.txt
password_generator_imbev-1.0.0.dist-info/LICENSE
password_generator_imbev-1.0.0.dist-info/WHEEL
password_generator_imbev-1.0.0.dist-info/METADATA
password_generator_imbev-1.0.0.dist-info/RECORD
