Metadata-Version: 2.1
Name: password-generator-imbev
Version: 1.0.0
Summary: A password generator written in Python.
License: GPL-3.0-only
Author: Isaac Beverly
Requires-Python: >=3.8,<4.0
Classifier: License :: OSI Approved :: GNU General Public License v3 (GPLv3)
Classifier: Programming Language :: Python :: 3
Classifier: Programming Language :: Python :: 3.10
Classifier: Programming Language :: Python :: 3.8
Classifier: Programming Language :: Python :: 3.9
